invisibl_aether_sdk/__init__.py
invisibl_aether_sdk/auth/__init__.py
invisibl_aether_sdk/auth/auth.py
invisibl_aether_sdk/exceptions/__init__.py
invisibl_aether_sdk/exceptions/exceptions.py
invisibl_aether_sdk/guardrails/__init__.py
invisibl_aether_sdk/guardrails/guardrails.py
invisibl_aether_sdk/model/__init__.py
invisibl_aether_sdk/model/aether_llm.py
invisibl_aether_sdk/utils/__init__.py
invisibl_aether_sdk/utils/utils.py
invisibl_aether_sdk-0.1.0.dist-info/METADATA
invisibl_aether_sdk-0.1.0.dist-info/WHEEL
invisibl_aether_sdk-0.1.0.dist-info/RECORD
