Metadata-Version: 2.1
Name: invisibl-aether-sdk
Version: 0.1.0
Summary: The Python SDK for Invisibl's Aether platform.
Author: Invisibl Team
Author-email: aether@invisibl.io
Requires-Python: >=3.9.12,<4.0.0
Classifier: Programming Language :: Python :: 3
Classifier: Programming Language :: Python :: 3.10
Classifier: Programming Language :: Python :: 3.11
Classifier: Programming Language :: Python :: 3.12
Requires-Dist: pyctcdecode (>=0.5.0,<0.6.0)
Requires-Dist: python-dotenv (>=1.0.1,<2.0.0)
Requires-Dist: requests (>=2.32.3,<3.0.0)
